devtools_regex_tester/__init__.py
devtools_regex_tester-1.0.1.dist-info/METADATA
devtools_regex_tester-1.0.1.dist-info/WHEEL
devtools_regex_tester-1.0.1.dist-info/top_level.txt
devtools_regex_tester-1.0.1.dist-info/RECORD
