Metadata-Version: 2.1
Name: devtools-regex-tester
Version: 1.0.1
Summary: Regex tester
Home-page: https://devtools.at/tools/regex-tester
Author: DevTools.at
Author-email: hello@devtools.at
Project-URL: Homepage, https://devtools.at/tools/regex-tester
Project-URL: Repository, https://github.com/devtools-at/regex-tester
Classifier: Development Status :: 4 - Beta
Classifier: Intended Audience :: Developers
Classifier: License :: OSI Approved :: MIT License
Classifier: Programming Language :: Python :: 3
Requires-Python: >=3.8
